maxlength_folder/__init__.py
maxlength_folder-0.2.1.dist-info/DESCRIPTION.rst
maxlength_folder-0.2.1.dist-info/METADATA
maxlength_folder-0.2.1.dist-info/RECORD
maxlength_folder-0.2.1.dist-info/WHEEL
maxlength_folder-0.2.1.dist-info/metadata.json
maxlength_folder-0.2.1.dist-info/top_level.txt
