Metadata-Version: 2.0
Name: maxlength-folder
Version: 0.2.1
Summary: Handle files and folder which exceeds themaximum length of filesystems
Home-page: https://github.com/FRReinert/Maxlength_folder
Author: Fabricio Roberto reinert
Author-email: fabricio.reinert@live.com
License: MIT license
Keywords: maxlength_folder,NTFS,maxlength,filesystem
Platform: UNKNOWN
Classifier: Development Status :: 2 - Pre-Alpha
Classifier: Intended Audience :: Developers
Classifier: License :: OSI Approved :: MIT License
Classifier: Natural Language :: English
Classifier: Programming Language :: Python :: 3.6
